{"aliases":["1301","1301c","i’m_telling_you,_ii_don’t_know_what_you’re_talking_about!","im_telling_you_ii_dont_know_what_youre_talking_about","i’mtellingyou,iidon’tknowwhatyou’retalkingabout!","imtellingyouiidontknowwhatyouretalkingabout","im","telling","ii","dont","know","what","youre","talking","about","i’m","you,","don’t","you’re","about!","ityidkwyta","itidkwyta"],"author":"775954146075082752","title":"I’m telling you, ii don’t know what you’re talking about!","color":null,"iconURL":null,"imageURL":null,"params":{"uno_color":"❄️","base":"False"},"fields":[],"meta":{"cannot_spawn":"true","spawn_as":"uno_color:❄️","color_choices":"❄️","post":"1301c"},"desc":"Post 1301c\n- Choose a player.\n- Draw **Fine. You want to see what happens so bad?**","id":1041}