{"aliases":["1010","fortune_teller_control","fortunetellercontrol","fortune","teller","control","ftc"],"author":"765276088183029810","title":"Fortune Teller Control","color":null,"iconURL":null,"imageURL":null,"params":{"uno_color":"<:rgby:1107167371048788028>","base":"False"},"fields":[],"meta":{"spawn_as":"uno_color:<:red:1106234051129507932>,<:blue:1106234079055200378>,<:green:1106234108042031166>,<:yellow:1106234135384699023>","color_choices":"<:rgby:1107167371048788028>","post":"1010"},"desc":"Post 1010\n- Discard all <:tarot:1106300551525826661> cards in all player's hands.","id":1336}