{"aliases":["749","boner_explosion","bonerexplosion","boner","explosion","be"],"author":"775954146075082752","title":"Boner Explosion","color":null,"iconURL":null,"imageURL":null,"params":{"uno_color":"<:bones:1118750770133737565>","base":"False"},"fields":[],"meta":{"spawn_as":"uno_color:<:bones:1118750770133737565>","color_choices":"<:bones:1118750770133737565>","post":"749"},"desc":"Post 749\n- All other players gain cards from your graveyard as equally as possible.","id":1597,"locked":false}