{"aliases":["360","just_an_actual_fucking_bomb","justanactualfuckingbomb","just","actual","fucking","bomb","jaafb","jafb"],"author":"655633028516937729","title":"Just an actual fucking bomb","color":null,"iconURL":null,"imageURL":null,"params":{"uno_color":"<:black:1106265022453268530>","base":"False"},"fields":[],"meta":{"spawn_as":"uno_color:<:black:1106265022453268530>","color_choices":"<:black:1106265022453268530>","post":"360"},"desc":"Post 360\n-Put a bomb on the table. The first person to say “I want to attempt to defuse the bomb” will attempt to defuse the bomb\n-The person who played the card must create 3 challenges for the defuser to attempt\n-If the person who is defusing the bomb fails one of the challenges, it explodes and they leave the game (they fucking die)\n-If nobody defuses the bomb, then the deck explodes scattering cards everywhere, causing everyone to gain 5 cards except for the person who played this card, because they’re wearing bomb gear","id":1975}