{"aliases":["304","drill_for_oil","drillforoil","drill","for","oil","dfo"],"author":"765276088183029810","title":"Drill for Oil","color":null,"iconURL":null,"imageURL":null,"params":{"uno_color":"<:blue:1106234079055200378> <:green:1106234108042031166> <:red:1106234051129507932> <:yellow:1106234135384699023>","base":"False"},"fields":[],"meta":{"spawn_as":"uno_color:<:blue:1106234079055200378>,<:green:1106234108042031166>,<:red:1106234051129507932>,<:yellow:1106234135384699023>","color_choices":"<:blue:1106234079055200378> <:green:1106234108042031166> <:red:1106234051129507932> <:yellow:1106234135384699023>","post":"304"},"desc":"Post 304\n- When you play this, remove cards from the play pile until you either reach the last card or reach a black card.\n- Cards that were removed from the play pile are evenly distributed to your neighbors.","id":2030}