{"aliases":["2112","hydro_power","hydropower","hydro","power","hp"],"author":"298205270201597955","title":"Hydro Power","color":null,"iconURL":null,"imageURL":null,"params":{"uno_color":"🌊","base":"False"},"fields":[],"meta":{"spawn_as":"uno_color:🌊","color_choices":"🌊","post":"2112"},"desc":"Post 2112\n- Draw a 🌊 card for each <:trinket:1141745128898310144> card in your hand, 🆔/<:discordian:1119395375896338512>/<:void:1119855990263775283> card in your Identity Zone, and currently active <:outsiders:1108173904062722118>/<:enchantment:1107516323426213888> card played by you.","id":256}