{"aliases":["2011","zombie_bite","zombiebite","zombie","bite","zb"],"author":"298205270201597955","title":"Zombie Bite","color":null,"iconURL":null,"imageURL":null,"params":{"uno_color":"<:grave:1119394182310670366>","base":"False"},"fields":[],"meta":{"spawn_as":"uno_color:<:grave:1119394182310670366>","color_choices":"<:grave:1119394182310670366>","post":"2011"},"desc":"Post 2011\n- Target a player.\n- After 4 of their turns, unless they have fewer cards than you or you have been **Destroyed**, the target will be **Destroyed**.","id":368}