{"aliases":["1983","stone_hammer","stonehammer","stone","hammer","sh"],"author":"298205270201597955","title":"Stone Hammer","color":"168f7d","iconURL":"https://cdn.discordapp.com/attachments/1107710055425519636/1294850944403640393/game_die.png","imageURL":null,"params":{"uno_color":"🎲+<:weapon:1107519313075785768>","base":"False"},"fields":[],"meta":{"spawn_as":"uno_color:🎲,<:weapon:1107519313075785768>","color_choices":"🎲+<:weapon:1107519313075785768>","post":"1983"},"desc":"Post 1983\n- Input any number to play this card.\n- The next player receives half the inputted number of **Card Shards**, rounded up.\n- If you input a 10, one of the next player's cards also gets **Stoned**.","id":397}