{"aliases":["1929","battle_axe","battleaxe","battle","axe","ba"],"author":"298205270201597955","title":"Battle Axe","color":"168f7d","iconURL":"https://cdn.discordapp.com/attachments/1107710055425519636/1294850944403640393/game_die.png","imageURL":null,"params":{"uno_color":"🎲+<:weapon:1107519313075785768>","base":"False"},"fields":[],"meta":{"spawn_as":"uno_color:🎲,<:weapon:1107519313075785768>","color_choices":"🎲+<:weapon:1107519313075785768>","post":"1929"},"desc":"Post 1929\n- Input a 3 or lower to play this card.\n- The next player draws cards equal to 2x the number of the die.\n- Alternatively, may be used on a <:builder:1119843481700012103> card to deal one hit to it.\n- This card will break any <:builder:1119843481700012103> card of the Wood subtype in one play.","id":447}