{"aliases":["1778","holy_water","holywater","holy","water","hw"],"author":"298205270201597955","title":"Holy Water","color":null,"iconURL":null,"imageURL":null,"params":{"uno_color":"<:holy:1120560132150022184>+🌊","base":"False"},"fields":[],"meta":{"spawn_as":"uno_color:<:holy:1120560132150022184>,🌊","color_choices":"<:holy:1120560132150022184>+🌊","post":"1778"},"desc":"Post 1778\n- Choose a player.\n- If their hand has any card of evil origin (having at least one color out of <:grave:1119394182310670366>, <:bones:1118750770133737565>, <:void:1119855990263775283>, <:rulebreaker:1120899966555127899>, <:monopoly:1171651746762866799>, or <:gloom:1187518684143550605>), that player gets **Destroyed**.\n- Otherwise, they get to discard a card of their choosing.","id":592}