{"aliases":["1704","double-edged_sword","doubleedgedsword","double","edged","sword","des"],"author":"298205270201597955","title":"Double-Edged Sword","color":"53342e","iconURL":"https://cdn.discordapp.com/emojis/1106732963577729055.webp","imageURL":null,"params":{"uno_color":"<:deck:1106732963577729055> (Neutral)","base":"False"},"fields":[],"meta":{"spawn_as":"uno_color:<:deck:1106732963577729055>","color_choices":"<:deck:1106732963577729055>","deck_type":"Neutral","post":"1704"},"desc":"Post 1704\n- Draw one random <:deck:1106732963577729055> Positive and one random <:deck:1106732963577729055> Negative card, and then play them both at once.","id":657}