{"aliases":["1380","aw_hell_naw","awhellnaw","aw","hell","naw","ahn"],"author":"775954146075082752","title":"Aw Hell Naw","color":null,"iconURL":null,"imageURL":null,"params":{"uno_color":"<:inferno:1118594776716021780>","base":"False"},"fields":[],"meta":{"spawn_as":"uno_color:<:inferno:1118594776716021780>","color_choices":"<:inferno:1118594776716021780>","post":"1380"},"desc":"Post 1380\n- Can also be played if anyone plays a card (even out of turn)\n- That card’s post is removed, and the card doesn’t get played.","id":965}