{"aliases":["23","bodyswapper","bs"],"author":"298205270201597955","title":"Bodyswapper","params":{"faction":"Neutral","subalignment":"Chaos","unique":"False","attack":"None","defense":"Basic"},"fields":[{"name":"Abilities:","value":"- Swap: Choose a player. You become their role and force them to become a Bodyswapper."},{"name":"Attributes:","value":"If you're still a Bodyswapper by the time the game ends, you lose."},{"name":"Goal:","value":"Swap with someone and follow your new role's goal."}],"meta":{},"desc":"Post 23","id":0}