{"aliases":["4479","visionary"],"author":"329331408269213696","title":"Visionary","color":null,"iconURL":null,"imageURL":null,"params":{"faction":"Peasant","subalignment":"Evil","unique":"False","attack":"None","defense":"Basic Auto-Vest against Evils"},"fields":[{"name":"Abilities:","value":"- During the day, choose three players to Test."},{"name":"Attributes:","value":"- Tested players will be informed. In addition to their usual abilities, they can choose to amputate any number of limbs, from 0-3. For each limb amputated, they blackmail themselves for a day.\n- The player who amputated the most number of limbs becomes Enlightened, gaining a basic auto-vest. If players tie, no one is Enlightened.\n- Evil players are informed of the other players in the test.\n- If an evil player is Enlightened, they can instead choose another player in the test to blackmail."},{"name":"Destiny:","value":"Enlighten three players, at least one of which must be evil."},{"name":"Goal:","value":"Have each living Peasant fulfill their Destiny."}],"meta":{},"desc":"Post 4479\n*“Truth cannot be imparted,” said Kline. “It must be inflicted.”*\n- Brian Evenson, *Last Days*","id":1178}