{"aliases":["5100","i_forgor","iforgor","forgor"],"author":"765276088183029810","title":"I forgor","color":null,"iconURL":null,"imageURL":null,"params":{"faction":"Town","subalignment":"Support","unique":"False","attack":"None","defense":"None"},"fields":[{"name":":","value":"(\nAttack: None\nDefense: None"},{"name":"Abilities:","value":"- Remember a dead town role, becoming that role. You cannot remember unique roles or Town Power roles."},{"name":"Attributes:","value":"- At the start of the game, you do not know you are **I forgor**. You are instead given another Town Support role, having that role's abilities/attributes. At the end of N2, you lose that role and learn you are **I forgor**."},{"name":"Goal:","value":"Kill all who oppose the Town __**or**__ kill all who oppose the Daily Streak Faction."}],"meta":{},"desc":"Post 5100","id":1430,"locked":false}