{"aliases":["60","medium","med"],"author":"343053472007979008","title":"Medium","params":{"faction":"Town","subalignment":"Support","unique":"False","attack":"None","defense":"None"},"fields":[{"name":"Abilities:","value":"- While dead, during the day, choose a player to séance."},{"name":"Attributes:","value":"- You will be able to talk with your target the next night.\n- While alive, you can talk with the dead at night.\n- All messages sent by you to the dead or while séancing appear to have been sent by “Medium”."}],"meta":{},"desc":"Post 60","id":146}