{"aliases":["4959",":birdgun:","birdgun"],"author":"765276088183029810","title":":birdgun:","color":null,"iconURL":null,"imageURL":null,"params":{"faction":"Town","subalignment":"Killing","unique":"False","attack":"Basic","defense":"None"},"fields":[{"name":"Abilities:","value":"- Shoot someone at night, dealing a basic attack."},{"name":"Attributes:","value":"- Since you are a bird and can fly, your visits are astral and you cannot be roleblocked.\n- If you shoot a town member, you lose your ability, even if they live.\n- __**Part of the Daily Streak Faction**__ - If part of the DSF, there is no penalty for killing Town members."},{"name":"Goal:","value":"Kill all who oppose the Town"}],"meta":{},"desc":"Post 4959\n*its a bird*","id":1540,"locked":false}