{"aliases":["4868","duwii-gone_with_the_wind","duwiigonewiththewind","duwii","gone","wind","dgwtw","dgw"],"author":"765276088183029810","title":"Duwii-Gone with the Wind","color":null,"iconURL":null,"imageURL":null,"params":{"faction":"Neutral","subalignment":"Killing","unique":"False","attack":"Unstoppable","defense":"Basic"},"fields":[{"name":"Abilities:","value":"- Make someone gone with the wind, dealing an unstoppable attack to them."},{"name":"Attributes:","value":"- Players you make gone with the wind will have their abilities in the past erased. For example, if your target gave somebody permanent basic defense, that wouldn't be the case anymore.\n- You clean targets you kill.\n- __**Part of the Daily Streak Faction**__"},{"name":"Goal:","value":"Kill all who oppose you."}],"meta":{},"desc":"Post 4868\n*I have now upgraded from copyright infringement to identity theft!*","id":1596,"locked":false}