{"aliases":["922","kaze"],"author":"277074946432172032","title":"Kaze","color":null,"iconURL":null,"imageURL":null,"params":{"faction":"Fox","subalignment":"Beta","unique":"False","attack":"None","defense":"None"},"fields":[{"name":"Abilities:","value":"Kaze is a carrier of the wind. Kaze has the ability to pick up on the wind currents and alter the weather of certain areas. At night they are able to force someone to stay inside due to strong winds. Effectively roleblocking them.\nAttributes:\n- Kaze can not perform the factional kill and roleblock someone at the same time\n- If no fox heads have been rolled roll a fox head"}],"meta":{},"desc":"Post 922","id":1867,"locked":false}