{"aliases":["4156","high_traveler","hightraveler","high","traveler","ht"],"author":"958932086159450123","title":"High Traveler","color":null,"iconURL":null,"imageURL":null,"params":{"faction":"High","subalignment":"Ancestor","unique":"False","attack":"None","defense":"None"},"fields":[{"name":"Abilities:","value":"Force every player into one player (2 uses)"},{"name":"Attributes:","value":"- Your ability will fail if a High Ancestor was not lynched the previous day"},{"name":"Goal:","value":"High Ancestor goal"}],"meta":{},"desc":"Post 4156","id":1965,"locked":false}