{"aliases":["3406","liar"],"author":"655633028516937729","title":"Liar","color":null,"iconURL":null,"imageURL":null,"params":{"faction":"Neutral","subalignment":"Evil","unique":"False","attack":"None","defense":"None"},"fields":[{"name":"Abilities:","value":"-Once per game, you may make a public statement anonymously. This statement has to be a lie."},{"name":"Attributes:","value":"-This statement is seen to have come from a different role of your choice that is capable of displaying a message to all townies\n-3 statements you make during the day must be lies. If they’re not, you’re modkilled. You may not tell the same lie more than once per day\n-If a member of the good faction confirms that they believe or agree with one of your lies, you learn their role at the start of the night phase. If multiple people do so, you do not learn which role belongs to who\n-If someone points out that what you said is a lie, your role is publicly revealed"},{"name":"Goal:","value":"Tell a minimum of 15 lies without being caught"}],"meta":{},"desc":"Post 3406\n_They’re not harmful, you see! They just… benefit my own agenda. A little white lie if you will!_","id":2465,"locked":false}