{"aliases":["3151","renegade"],"author":"1045218960951484527","title":"Renegade","color":null,"iconURL":null,"imageURL":null,"params":{"faction":"Neutral","subalignment":"Killing","unique":"False","attack":"None","defense":"Basic"},"fields":[{"name":"Abilities:","value":"**Hide**(Day) Watch the town from the shadows. You don't get to vote and you cannot be voted\n**Kill** (Night) Attack another player."},{"name":"Attributes:","value":"*Attack* goes up 1 stage every two player deaths (None --> Basic --> Powerful --> Unstoppable).*\nOnce *Attack* has maxed out, *Defense* begins to increase in the same way.\nIf *Attack* and *Defense* are maxed, you will *Rampage*.\nYou are *roleblock immune*.\n*Goal*: Eliminate the rest of the factions~"}],"meta":{},"desc":"Post 3151","id":2677,"locked":false}