{"aliases":["19","-02271996","-2271996","i_hate_game_19","ihategame19","hate","game","ihg1","hg1"],"author":"189932350791090176","title":"I Hate Game 19","color":null,"iconURL":null,"imageURL":null,"params":{"faction":"Neutral","subalignment":"Other","unique":"False","attack":"None","defense":"None"},"fields":[],"meta":{"cannot_spawn":"true"},"desc":"Post -02271996\nIf your target's role is Day Vigilante, Veteran, Veteran't, Ancient Ghost, or Hey i just met you, remove them from the game.\nYou will prevent any and all attacks made during the day phase.\nAll visits are Astral on Night 1.","id":2784,"locked":false}