{"aliases":["4269","converter"],"author":"906936197266423839","title":"Converter","color":null,"iconURL":null,"imageURL":null,"params":{"faction":"Neutral","subalignment":"Chaos","unique":"False","attack":"None","defense":"Basic"},"fields":[{"name":"Abilities:","value":"- Convert any other player in the game. They will turn into ANY role that can still win the game (i.e if a role has already won, or physically cannot win the game, reroll the conversion)\n- You will know their new role."},{"name":"Attributes:","value":"- If this slot is converted, it keeps the ability and attribute of this role, but gains the new wincon. Can be converted again, no matter what."},{"name":"Goal:","value":"Convert 3 people and see one of them win"}],"meta":{},"desc":"Post 4269","id":2809,"locked":false}