{"aliases":["-13","murderous_chess_grandmaster","murderouschessgrandmaster","murderous","chess","grandmaster","mcg"],"author":"536648090183270441","title":"Murderous Chess Grandmaster","color":null,"iconURL":null,"imageURL":null,"params":{"faction":"Neutral","subalignment":"Killing","unique":"False","attack":"Basic","defense":"Basic"},"fields":[{"name":"Abilities:","value":"-Beat someone to death with your chessboard every night."},{"name":"Goal:","value":"NK goal"}],"meta":{"cannot_spawn":"true"},"desc":"Post -13","id":3117,"locked":false}