{"aliases":["2222","scribblenaut"],"author":"654448067969548338","title":"Scribblenaut","color":null,"iconURL":null,"imageURL":null,"params":{"faction":"Neutral","subalignment":"Chaos","unique":"False","attack":"None","defense":"None"},"fields":[{"name":"Abilities:","value":"- Choose an adjective to give to someone, the host will give them a custom Passive/Effect/Debuff based on the selected adjective."},{"name":"Attributes:","value":"\n\n- You may self-target once, the adjective you give yourself will not count for your goal.\n- If a player dies with an adjective, it will be added behind their role name on death. (Ex: Energized Mafioso)"},{"name":"Goal:","value":"Make sure 2 of your adjectives affect the game in some way. (Causing a death, Protecting someone, Giving info)"}],"meta":{},"desc":"Post 2222","id":351}