{"aliases":["478","synesthesia"],"author":"189932350791090176","title":"Synesthesia","color":null,"iconURL":null,"imageURL":null,"params":{"faction":"Coven","subalignment":"Evil","unique":"False","attack":"None (Basic)","defense":"None"},"fields":[{"name":"Abilities:","value":"- Choose a player and a sense to perceive them with."},{"name":"Attributes:","value":"- You will perform an action to your target based on the sense that you chose as well as one other random sense.\n- Your sense of sight will reveal your target's faction.\n- Your sense of smell will reveal how many charges of any limited-use abilities your target has remaining. If they do not have a limited-use ability, you will be notified about this.\n- Your sense of touch will reveal your target's attack and defense values.\n- Your sense of hearing will reveal if your target has any night chats and the last message sent in all of them if they do have any night chats.\n- Your sense of taste will reveal if your target has any non-death immunities, such as roleblock or redirection immunity.\n- With the Necronomicon, you unlock the sixth sense, which deals an Astral Basic attack to your target."}],"meta":{},"desc":"Post 478\n*I see, smell, feel, hear, and taste dead people. All at once.*","id":3564,"locked":false}