{"aliases":["1331","sleep_rock","sleeprock","sleep","rock","sr"],"author":"765276088183029810","title":"Sleep Rock","color":null,"iconURL":null,"imageURL":null,"params":{"faction":"Rock","subalignment":"Support","unique":"False","attack":"Basic","defense":"None"},"fields":[{"name":"Abilities:","value":"> Help someone sleep at night or put them to sleep forever."},{"name":"Attributes:","value":"> If you help someone sleep, they will be roleblocked.\n\n> If you put them to sleep forever, you will attack them. This can only be done once."}],"meta":{},"desc":"Post 1331\n*\"Give someone sleep and you help them for a day. Give someone the ability to sleep forever and help them for the rest of their afterlife.\"*","id":4194,"locked":false}