{"aliases":["2366","polymorph"],"author":"918726268810297364","title":"Polymorph","color":null,"iconURL":null,"imageURL":null,"params":{"faction":"Neutral","subalignment":"Evil","unique":"False","attack":"Depends","defense":"Depends"},"fields":[{"name":"Abilities:","value":"Thrice per game, you may choose any GiM, classic ToS, ToS FM, Camp Cadaver or Throne of Lies role to gain the abilities, attributes, attack and defense of until you use this ability again. You cannot select Post 2366 Polymorph."},{"name":"Goal:","value":"You win if the town loses, whether you are dead or alive."}],"meta":{},"desc":"Post 2366","id":4989,"locked":false}