{"aliases":["5174","british_stabber","britishstabber","british","stabber","bs"],"author":"654448067969548338","title":"British Stabber","color":null,"iconURL":null,"imageURL":null,"params":{"faction":"Brainless","subalignment":"Assassin","unique":"False","attack":"Powerful","defense":"Basic"},"fields":[{"name":"Abilities:","value":"- **Royal Stab**: Select a player to stab during the night. The stab bypasses Basic defense. If the target survives, they will bleed and die the following night if not healed. (X uses: Infinite)\n- **Tea Time**: Once per game, select a player to invite for tea. Both you and the selected player will be immune to all abilities that night and will learn each other's roles."},{"name":"Attributes:","value":"- During Tuesday and Friday, **Royal Stab** will bypass Powerful defense and the bleed effect will bypass healing.\n- **Tea Time**: If used on Tuesday or Friday, it can be used again later in the game.\n- Immune to Roleblocks and Control on Tuesdays and Fridays.\n- Leaves a distinct British-themed death note."}],"meta":{},"desc":"Post 5174","id":5371,"locked":false}