{"aliases":["3331","tavernkeeper"],"author":"329331408269213696","title":"Tavernkeeper","color":null,"iconURL":null,"imageURL":null,"params":{"faction":"Storyteller","subalignment":"Introduction","unique":"False","attack":"None","defense":"Basic (Autovest x1)"},"fields":[{"name":"Abilities:","value":"- At night, choose someone to Entice.\n- Enticed players will be controlled into visiting you.\n- Enticed players won't attack you, and they won't receive night notifications while they are Enticed other than they slept safely.\n- You can't Entice the same player twice in a row."},{"name":"Attributes:","value":"- You learn the name of all players who visit you at the end of the night.\n- If 2 or more players visit you, the Introduction becomes \"*The misguided protagonist begins in a tavern, hoping to acquire riches.*\" When the story is completed with this Introduction, you astrally roleblock all good players."},{"name":"Goal:","value":"Tell a full story."}],"meta":{},"desc":"Post 3331\n\"*My tavern has had an unusual amount of 'adventurers' after the war started.*\"","id":656}