{"aliases":["3687","mole"],"author":"329331408269213696","title":"Mole","color":null,"iconURL":null,"imageURL":null,"params":{"faction":"Town","subalignment":"Investigative","unique":"False","attack":"None","defense":"None"},"fields":[{"name":"Abilities:","value":"- At night, choose up to 3 players to Test. For each player, learn if they are an ally (non-evil role) or dissident (evil role)."},{"name":"Attributes:","value":"- If ANY tested players are a kill-capable dissident, they deal a basic attack to you instead of their normal action, and you are cleaned."},{"name":"Goal:","value":"Town goal"}],"meta":{},"desc":"Post 3687","id":721,"locked":false}