{"aliases":["army"],"author":"298205270201597955","title":"Army","color":"e8d578","iconURL":"https://cdn.discordapp.com/emojis/1013454909099749468.webp?size=40&quality=lossless","params":{"type":"Good"},"fields":[{"name":"Subalignments:","value":"Command, Support, Investigative, Protective, Killing"},{"name":"Features:","value":"- 1536: Marshal and at least one Army Protective will always spawn.\n- No factional chat\n- No factional kill\n- If the Marshal dies, the Army has three days to win. After that, if the Army would win, the game is declared a draw instead."},{"name":"Goal:","value":"Eliminate all who would not follow martial law."}],"meta":{"inherit_fields":"Goal:Eliminate all who would not follow martial law."},"id":40}