{"aliases":["pirate"],"author":"361152876048809984","title":"Pirate","color":null,"iconURL":null,"imageURL":null,"params":{"faction":"Chaos","type":"Support","unique":"False"},"fields":[{"name":"Passives:","value":"- Plunder: Gain a non-special card of your choice every Night phase. [Activates D2] \n- Loot: Whenever you Kill someone, take all of the cards they did not use."},{"name":"Abilities:","value":"- Pillage: Pick 3 players. Take a random card from each of them immediately. [1 use]\n- Threaten: When in a trade, take all cards from the opposing player immediately. [1 use, Unique]\n- Coerce: Pick a player. See their entire hand with modifiers. Play up to 2 cards for them. [1 use, Unique]\n- Intimidate: Prevent half of True Order members from drawing this phase. [1 use, Unique]"}],"meta":{"track_message_id":"1312154583161634896"},"desc":null,"id":32}