{"aliases":["conqueror"],"author":"361152876048809984","title":"Conqueror","color":null,"iconURL":null,"imageURL":null,"params":{"faction":"Outsider","type":"Turbulent","unique":"True"},"fields":[{"name":"Passives:","value":"- Hatred: Every 5th attack you make against the King will be Upgraded.\n- Suffocate: If you are in the same room with the King, you will deal them 1 HP of unblockable damage at the end of the phase. You may choose to not have this activated.\n- Exclusion: If you are in the game, the King will not be Outsider-aligned."},{"name":"Abilities:","value":"- Track: Learn where the King visits tonight at the end of the phase. [2 uses, Day]\n- Hidden Key: Go to the King’s Quarters. [1 use, UOR2]\n- Backup: Draw 2 extra cards immediately. [2 uses, 2 CD]\n- Prepared: Upgrade a card. [1 use, Unique, UOR2]"},{"name":"Goal:","value":"Live to Kill the King."}],"meta":{"track_message_id":"1312155119466319983"},"desc":null,"id":49}