{"aliases":["3117","electric_boogaloo","electricboogaloo","electric","boogaloo","eb"],"author":"327918538419601409","title":"Electric Boogaloo","color":null,"iconURL":null,"imageURL":null,"params":{"faction":"Zombie","subalignment":"Hero","unique":"True","attack":"Overkill","defense":"Basic"},"fields":[{"name":"Abilities:","value":"- Synchronize two players' movements with another's, redirecting the two players to the third player's target. If the third player has multiple targets, it will be the first one.\n- Strike down a player at night. If they were ever attacked but survived somehow, kill them. (3 uses)"},{"name":"Attributes:","value":"- You only visit your third target with your first ability.\n- If your targets are redirected into visiting you, they will all be roleblocked.\n- Roleblock and redirect immune"}],"meta":{},"desc":"Post 3117\n*Are you shocked that I simply didn't leave the text as \"disco is undead?\"*","id":1206,"locked":false}