{"aliases":["4890","unidentified_floating_shark","unidentifiedfloatingshark","unidentified","floating","shark","ufs"],"author":"327918538419601409","title":"Unidentified Floating Shark","color":null,"iconURL":null,"imageURL":null,"params":{"faction":"Coven","subalignment":"Evil","unique":"False","attack":"Basic","defense":"None"},"fields":[{"name":"Abilities:","value":"- Summon a floating shark to patrol someone’s house at night."},{"name":"Attributes:","value":"- If your target is visited, your shark will bite all of their visitors, drawing their blood.\n- If your shark patrols at someone’s house whose blood was drawn, your shark will deal a Basic attack to them and not bite any visitors.\n- If your target is attacked by something other than yourself, your shark will increase the attack value of that attack by one.\n- With the Necronomicon, your shark will always deal a Basic attack to your target."}],"meta":{},"desc":"Post 4890","id":1584,"locked":false}