{"aliases":["4644","the_card_game_me_and_my_brother_made_up","thecardgamemeandmybrothermadeup","card","game","my","brother","made","up","tcgmambmu","cgmbmu"],"author":"521123471460270121","title":"The card game me and my brother made up","color":null,"iconURL":null,"imageURL":null,"params":{"faction":"Neutral","subalignment":"Other","unique":"False","attack":"None","defense":"None"},"fields":[{"name":"Abilities:","value":"*Game On* — During the day, challenge another player. The next time they and the host are both present, the host will ping them in their private channel. Once they send a message, the host will, if or when they're both still online, the host will tell them they have 120000 seconds to complete the following challenge:\n> - Beat you in a game of 2-deck Diamonds. Ask Rasen for how to play."},{"name":"Attributes:","value":"*Prize!* — If a challenged player successfully completes your challenge, they may convert into any role that references diamonds or Igu."},{"name":"Goal:","value":"Get a total of 64 diamonds across games"}],"meta":{},"desc":"Post 4644\n*twunawun*","id":1726,"locked":false}