{"aliases":["4134","doppelgänger","doppelgnger"],"author":"958932086159450123","title":"Doppelgänger","color":null,"iconURL":null,"imageURL":null,"params":{"faction":"Linchpin","subalignment":"Deception","unique":"False","attack":"None","defense":"None"},"fields":[{"name":"Abilties:","value":"Disguise a Linchpin"},{"name":"Attributes:","value":"- Astral visits\n- You may disguise them as any role that has spawned\n- They will be seen as that role and seen visiting that role’s target\n- The player with the role you disguised the Linchpin as will be seen as the Linchpin with visits and all"}],"meta":{},"desc":"Post 4134","id":1952,"locked":false}