{"aliases":["3456","spamton_neo","spamtonneo","spamton","neo","sn"],"author":"562746047596593163","title":"Spamton NEO","color":null,"iconURL":null,"imageURL":null,"params":{"faction":"Town","subalignment":"Killing","unique":"False","attack":"Basic","defense":"Immortal"},"fields":[{"name":"Abilities:","value":"- Select a player to veeerry slowly murder them. They die after two nights, assuming you haven't been roleblocked/controlled/redirected to someone else by then, and assuming they have not received protection of any kind in that time."},{"name":"Attributes:","value":"- Your target is aware that they are going to die.\n- You will continuously visit your target until they die.\n- You may attack another player while you're waiting on one to die already.\n- You can't die under any circumstances, including hanging. However, you lose automatically if you're the last Town."}],"meta":{},"desc":"Post 3456\n*DIDN'T YOU KNOW [Neo] IS FAMOUS FOR ITS HIGH DEFENSE!?*","id":2431,"locked":false}