{"aliases":["1904","beloved_beggar","belovedbeggar","beloved","beggar","bb"],"author":"298205270201597955","title":"Beloved Beggar","params":{"faction":"Gatherer","subalignment":"White","unique":"False","attack":"None","defense":"Powerful"},"fields":[{"name":"Abilities:","value":"- Generate (White) each night."},{"name":"Attributes:","value":"- While dead, another Gatherer may pay (White)(White)(4) to revive you as the 1904B Generous Soul."}],"meta":{},"desc":"Post 1904\n*Charity is rare on Innistrad, but kindness is always repaid.*","id":248}