{"aliases":["3286","zage_can_cope_tbh","zagecancopetbh","zage","cope","tbh","zcct","zct"],"author":"562746047596593163","title":"Zage Can Cope Tbh","color":null,"iconURL":null,"imageURL":null,"params":{"faction":"Neutral","subalignment":"Benign","unique":"False","attack":"None","defense":"None"},"fields":[{"name":"Abilities:","value":"- Roleblock a player."},{"name":"Attributes:","value":"- You roleblock all your visitors."},{"name":"Goal:","value":"Roleblock 75% of the numbers of players."}],"meta":{},"desc":"Post 3286","id":2554,"locked":false}