{"aliases":["3278","traptrix_pudica","traptrixpudica","traptrix","pudica","tp"],"author":"504813861950586891","title":"Traptrix Pudica","color":null,"iconURL":null,"imageURL":null,"params":{"faction":"-","subalignment":"Traptrix(Plant","unique":"False","attack":"None","defense":"None"},"fields":[{"name":"Abilities:","value":"-You may visit a player."},{"name":"Attributes:","value":"-Any player who visits you or you visit shrinks, lowering their attack value and defense value.\n-A shrunk player loses all abilities and attributes the host deems that they would need to have a moderate amount of height for."},{"name":"Goal:","value":"Slay everybody who would oppose you."}],"meta":{},"desc":"Post 3278\n*If you touch me, you will face hell.*","id":2562,"locked":false}