{"aliases":["3164","angel"],"author":"654448067969548338","title":"Angel","color":null,"iconURL":null,"imageURL":null,"params":{"faction":"KA","subalignment":"Spiritual","unique":"False","attack":"None","defense":"Hell-Bent"},"fields":[{"name":"Abilities:","value":"- **Sword**: Play any attacking card, it will be upgraded if possible. You may gain an additional use of this at any time by sacrificing any 3 cards. (0 uses)\n- **Save**: Pick a player and lose 2 HP. That player will gain death immunity this night and secretly be Lynchproof the next day. (2 uses)\n- **Ascend**: Sacrifice yourself this night. You may play cards when dead and draw 2 each night start. (1 use)"},{"name":"Attributes:","value":"- **Frail**: You die if you reach 1 HP, rather than 0."},{"name":"Goal:","value":"KA goal."}],"meta":{},"desc":"Post 3164","id":2665,"locked":false}