{"aliases":["953","soldier"],"author":"189932350791090176","title":"Soldier","color":null,"iconURL":null,"imageURL":null,"params":{"faction":"Town","subalignment":"Killing","unique":"False","attack":"Powerful","defense":"None"},"fields":[{"name":"Abilities:","value":"- Go on alert outside someone else's house each night. (3 uses)"},{"name":"Attributes:","value":"- When on alert, you will deal a Powerful attack to all players that visit your target that night.\n- You will not attack yourself with your ability."}],"meta":{},"desc":"Post 953\n*I took a strict drug-free oath when I applied for this position.*","id":3521,"locked":false}