{"aliases":["2261","abnormal_condition","abnormalcondition","abnormal","condition","ac"],"author":"417531120075407371","title":"Abnormal Condition","color":null,"iconURL":null,"imageURL":null,"params":{"faction":"Coven","subalignment":"Evil","unique":"False","attack":"Basic/Unstoppable","defense":"None"},"fields":[{"name":"Abilities:","value":"- Inflict disease on two players. This gives them Cold, or moves them to the next stage if they are already diseased.\n> Cold: Their defence is set to vulnerable.\n> Fever: They cannot vote.\n> Hell: They will be dealt a basic attack at the end of the next night.\n> Heaven: They gain invincible defence, and become fully death immune.\n> Seizure: All defence is removed, and they are dealt an unstoppable attack."},{"name":"Attributes:","value":"- Diseases only come into effect after they are applied.\n- At the end of every night, there's a 40% chance that diseased players will move onto the next stage without your involvement.\n- You always know which players are diseased and what stage they are at.\n- When you die, all diseases remain, and the chance of naturally progressing is increased to 75%.\n- With the Necronomicon, using your ability on an undiseased player will move them immediately to Hell instead of Cold."},{"name":"Goal:","value":"Make the other players forgive to the Coven."}],"meta":{},"desc":"Post 2261\n*I've never played this game in my life.*","id":3663,"locked":false}