{"aliases":["1921","defense_attorney","defenseattorney","defense","attorney","da"],"author":"174251652524539904","title":"Defense Attorney","color":null,"iconURL":null,"imageURL":null,"params":{"faction":"Coven","subalignment":"Evil","unique":"False","attack":"Variable","defense":"None"},"fields":[{"name":"Abilities:","value":"- At night, select a player. You will defend them from having low defense, meaning their defense level will be permanently upgraded by one level (two levels if you have the Necronomicon). With the Necronomicon, targeting a player with this ability will also defend them from living a life with imbalanced stats, dealing an attack to them which treats their defense level as the attack level and their attack level as the defense level, unless they are a member of the Coven. The defense gain effect always resolves before the attack effect."},{"name":"Attributes:","value":"- You may target yourself."}],"meta":{},"desc":"Post 1921\n*The best offense is a good defense. No, wait...*","id":3920,"locked":false}