{"aliases":["1159","essence_of_town","essenceoftown","essence","town","eot","et"],"author":"765276088183029810","title":"Essence of Town","color":null,"iconURL":null,"imageURL":null,"params":{"faction":"Coven","subalignment":"Evil","unique":"True","attack":"Varies","defense":"None"},"fields":[{"name":"Abilities:","value":"> Use the ability of a town role."},{"name":"Attributes:","value":"> The attributes of the town role will apply to you *unless* they harm you or prevent you from acting.\n\n> You may use any town role, even if it is not in the game.\n\n> You can only use each town role once.\n\n> You may only use two day abilities.\n\n> With the Necronomicon, you may use all night town roles several times, you may act twice at night (no using the same role twice in the same night), you may use all day ability townies once (once per day).\n\n> You cannot use Town (Power) roles."}],"meta":{},"desc":"Post 1159\n*\"Me when Essence of Town isn't a town role.\"*","id":4096,"locked":false}