{"aliases":["2955","silly_autovest_dude","sillyautovestdude","silly","autovest","dude","sad"],"author":"521123471460270121","title":"Silly Autovest Dude","color":null,"iconURL":null,"imageURL":null,"params":{"faction":"Neutral","subalignment":"Evil","unique":"False","attack":"None","defense":"None (Basic) (Powerful) (Invincible) (Overprotective)"},"fields":[{"name":"Abilities:","value":"- Give a player an autovest of any of the following defense values. You may only choose each once. Your autovests trigger before any other autovests.\n> - Overprotective\n> - Invincible\n> - Powerful\n> - Basic\n> - Aura\n> - Hellbent\n> - None\n> - Vulnerable"},{"name":"Attributes:","value":"- You have an Overprotective, an Invincible, a Powerful, and a Basic autovest. They trigger in that order."},{"name":"Goal:","value":"Live to see the Town lose the game."}],"meta":{},"desc":"Post 2955\n*A layer of X defense that can protect it from one attack. If a player with an autovest would be attacked multiple times at once, the autovest will block a random one of the attacks among the strongest ones that it can successfully block. for only $9.99!*","id":4661,"locked":false}