{"aliases":["2643","harp"],"author":"562746047596593163","title":"Harp","color":null,"iconURL":null,"imageURL":null,"params":{"faction":"Band","subalignment":"String","unique":"False","attack":"None","defense":"None"},"fields":[{"name":"Abilities:","value":"- Soothe a player, healing them, but roleblocking them.\n- (Rehearsal) Cause a distraction at a player's house, forcing their neighbors and their neighbors' visitors to visit them, then rehearse.\n- (Concert) Untune your strings, causing hearing issues, which prevents your target from seeing the day chat or talking in it. They also can't vote."},{"name":"Attributes:","value":"- Yes, you still roleblock Band members."}],"meta":{},"desc":"Post 2643","id":4836,"locked":false}