{"aliases":["2255","bomb_bob","bombbob","bomb","bob","bb"],"author":"562746047596593163","title":"Bomb Bob","color":null,"iconURL":null,"imageURL":null,"params":{"faction":"Neutral","subalignment":"Killing","unique":"False","attack":"Unstoppable","defense":"Powerful"},"fields":[{"name":"Abilities:","value":"- Make someone's name Bob. They can't change it anymore.\n- Bomb Bob. You can only bomb a single Bob per day."},{"name":"Goal:","value":"NK goal"}],"meta":{},"desc":"Post 2255","id":5090,"locked":false}