{"aliases":["5378","coroner-","coroner"],"author":"563491765576007680","title":"Coroner-","color":null,"iconURL":null,"imageURL":null,"params":{"faction":"Unseen","subalignment":"Investigative","unique":"False","attack":"None","defense":"None"},"fields":[{"name":"Abilities:","value":"- Learn if someone that was attacked and killed was your target tonight."},{"name":"Goal:","value":"Unseen goal"}],"meta":{"post":"5378","track_message_id":"1312617330882383894"},"desc":"Post 5378\n*Converted from Coroner+*","id":5570,"locked":false}