{"aliases":["5392","alignment_ritualist","alignmentritualist","alignment","ritualist","ar"],"author":"562746047596593163","title":"Alignment Ritualist","color":null,"iconURL":null,"imageURL":null,"params":{"faction":"Coven","subalignment":"Killing","unique":"False","attack":"Unstoppable","defense":"None"},"fields":[{"name":"Abilities:","value":"- Guess a player's alignment at night. If correct, you will deal an Astral Unstoppable attack to your target. 3 uses."},{"name":"Attributes:","value":"- If you guess incorrectly, your role is revealed to all players and your target lives.\n- With the Necronomicon, an incorrect guess will not reveal your role and you will instead deal a Basic Attack to your target. This is not Astral."},{"name":"Goal:","value":"Kill everyone who would oppose the Coven."}],"meta":{"post":"5392","track_message_id":"1317671529315700869"},"desc":"Post 5392\n*hated vfa? here you go!*","id":5584,"locked":false}