{"aliases":["3901","open_ended_roleplay_bit","openendedroleplaybit","open","ended","roleplay","bit","oerb"],"author":"329331408269213696","title":"Open Ended Roleplay Bit","color":null,"iconURL":null,"imageURL":null,"params":{"faction":"Neutral","subalignment":"Chaos","unique":"False","attack":"Basic","defense":"Basic"},"fields":[{"name":"Abilities:","value":"- At night, choose a player to attack.\n- During the day, choose a player to attack. 1 charge.\n- At night, choose any basic Town role from Town of Salem 2 to copy the ability of. Each ability must be unique from the last."},{"name":"Goal:","value":"Make a bit that the host deems was funny"}],"meta":{},"desc":"Post 3901","id":736}