{"aliases":["venom!","venom","ve"],"author":"298205270201597955","title":"Venom!","color":null,"iconURL":null,"imageURL":null,"params":{"category":"Attack","rarity":"Common","ammo_requirement":"1"},"fields":[{"name":"Range:","value":"2"}],"meta":{"targets":"1","damage":"0","alt_amt":"2","alt_txt":"apply Poisoned {alt_amt} to them","status":"y","on_process":"inflict_poison","range":"2","track_message_id":"1349774290374889584"},"desc":"If target doesn't defend, deal 0 damage and apply Poisoned 2 to them.\n\nPoisoned players take 1 damage per round for a set number of rounds. Stacking the effect only extends its duration. However, a single Medicine! can remove all Poison.\n\n-# Status effects take effect the round after application.\n-# Can't target self.\n","id":2}