{"aliases":["duel?!","duel"],"author":"361152876048809984","title":"Duel?!","color":null,"iconURL":null,"imageURL":null,"params":{"type":"Item","rarity":"Special","silent":"False"},"fields":[{"name":"Effect:","value":"Put 2 players into a Duel with each other. Whoever earns more card points at the end of the duel wins the duel and gets to gain a card of their choice. Whoever loses the duel takes 2 HP of unblockable damage.\n\n*Check Dueling for information about Duels. Check <#1191650444594909354> for information on card points.*"}],"meta":{"spawn_rate":"0.36","track_message_id":"1312140533438746725"},"desc":null,"id":36}